firecloud_api_cds/__init__.py
firecloud_api_cds/api.py
firecloud_api_cds/config.py
firecloud_api_cds/entity.py
firecloud_api_cds/errors.py
firecloud_api_cds/fccore.py
firecloud_api_cds/fiss.py
firecloud_api_cds/method.py
firecloud_api_cds/submission.py
firecloud_api_cds/supervisor.py
firecloud_api_cds/workspace.py
firecloud_api_cds-0.2.0.dist-info/METADATA
firecloud_api_cds-0.2.0.dist-info/WHEEL
firecloud_api_cds-0.2.0.dist-info/licenses/LICENSE
firecloud_api_cds-0.2.0.dist-info/RECORD
