Metadata-Version: 2.4
Name: firecloud-api-cds
Version: 0.2.0
Summary: Fork of broadinstitute/fiss
Project-URL: Homepage, https://github.com/broadinstitute/firecloud-api-cds
License: BSD 3-Clause License
License-File: LICENSE
Requires-Python: >=3.9
Requires-Dist: google-auth!=2.1.*,!=2.2.*,!=2.3.0,!=2.3.1,>=1.6.3
Requires-Dist: google-cloud-storage>=1.36.1
Requires-Dist: pydot>=4.0.0
Requires-Dist: six>=1.17.0
